pandas_to_pydantic/__about__.py
pandas_to_pydantic/__init__.py
pandas_to_pydantic/annotation_utils.py
pandas_to_pydantic/to_pydantic.py
pandas_to_pydantic-0.1.5.dist-info/METADATA
pandas_to_pydantic-0.1.5.dist-info/WHEEL
pandas_to_pydantic-0.1.5.dist-info/licenses/LICENSE
pandas_to_pydantic-0.1.5.dist-info/RECORD
