Metadata-Version: 2.4
Name: pandas-to-pydantic
Version: 0.1.5
Summary: Library for converting pandas dataframes to pydantic models
Project-URL: Documentation, https://github.com/magicalpuffin/pandas-to-pydantic#readme
Project-URL: Issues, https://github.com/magicalpuffin/pandas-to-pydantic/issues
Project-URL: Source, https://github.com/magicalpuffin/pandas-to-pydantic
Author-email: magicalpuffin <36088648+magicalpuffin@users.noreply.github.com>
License-Expression: MIT
License-File: LICENSE
Classifier: Development Status :: 4 - Beta
Classifier: Programming Language :: Python
Classifier: Programming Language :: Python :: 3.9
Classifier: Programming Language :: Python :: 3.10
Classifier: Programming Language :: Python :: 3.11
Classifier: Programming Language :: Python :: 3.12
Classifier: Programming Language :: Python :: 3.13
Classifier: Programming Language :: Python :: Implementation :: CPython
Classifier: Programming Language :: Python :: Implementation :: PyPy
Requires-Python: >=3.9
Requires-Dist: pandas>=2.0.0
Requires-Dist: pydantic>=2.0.1
